MANIFEST.in
README.md
gdata2pg.ini.default
pyproject.toml
requirements.txt
rollups.py
server.py
setup.py
tsd.sql
gdata2pg.egg-info/PKG-INFO
gdata2pg.egg-info/SOURCES.txt
gdata2pg.egg-info/dependency_links.txt
gdata2pg.egg-info/top_level.txt
libgd2pg/__init__.py
libgd2pg/config.py
libgd2pg/datamanager.py
libgd2pg/db.py
libgd2pg/error.py
libgd2pg/flask.py
libgd2pg/timer.py