Metadata-Version: 1.1
Name: gdata2pg
Version: 0.1.0
Summary: A data receiver for collectd that inserts data into a Postgres database for use with Grafana
Home-page: UNKNOWN
Author: Jay Deiman
Author-email: admin@splitstreams.com
License: GPLv2
Keywords: grafana http postgresql
Platform: UNKNOWN
Classifier: Development Status :: 4 - Beta
Classifier: Intended Audience :: Developers
Classifier: License :: OSI Approved :: GNU General Public License v2 (GPLv2)
Classifier: Programming Language :: Python :: 3
Classifier: Topic :: System :: Monitoring
